ElectricalMM/Electrical_MM.py
ElectricalMM/__init__.py
ElectricalMM/general_functions.py
ElectricalMM/specific_electrical.py
MihkelMagicElectrical-0.8.0.dist-info/LICENSE.txt
MihkelMagicElectrical-0.8.0.dist-info/METADATA
MihkelMagicElectrical-0.8.0.dist-info/WHEEL
MihkelMagicElectrical-0.8.0.dist-info/top_level.txt
MihkelMagicElectrical-0.8.0.dist-info/RECORD
