Metadata-Version: 2.1
Name: MihkelMagicElectrical
Version: 0.8.0
Summary: Automated analysis of superconductor electrical data.
Home-page: https://github.com/mihkelKR/MihkelMagic_Electrical
Author: Mihkel Kaarel Raidal
Author-email: m.k.raidal@gmail.com
License: MIT
Platform: UNKNOWN
Classifier: Programming Language :: Python :: 3
Classifier: License :: OSI Approved :: MIT License
Classifier: Operating System :: OS Independent
Requires-Python: >=3.9
License-File: LICENSE.txt
Requires-Dist: numpy (>=1.21.1)
Requires-Dist: xlwt (>=1.3.0)
Requires-Dist: pandas (>=1.3.1)
